{
   "image_filename": "XBIB-U-SS.jpg",
   "complete": null,
   "labels": [
      {
         "label_type": "box",
         "label_class": "C",
         "centre": {
            "x": 271.32998795838415,
            "y": 94.28558830602925
         },
         "size": {
            "x": 16.65612614745646,
            "y": 8.615237662477483
         },
         "object_id": 1
      },
      {
         "label_type": "box",
         "label_class": "C",
         "centre": {
            "x": 245.3406876765771,
            "y": 121.99793612033183
         },
         "size": {
            "x": 11.77415813871923,
            "y": 19.240697446199732
         },
         "object_id": 2
      },
      {
         "label_type": "box",
         "label_class": "C",
         "centre": {
            "x": 260.70452817466196,
            "y": 124.58250741907506
         },
         "size": {
            "x": 8.040888484979007,
            "y": 15.794602381208719
         },
         "object_id": 3
      },
      {
         "label_type": "box",
         "label_class": "C",
         "centre": {
            "x": 275.49401949524827,
            "y": 124.15174553595119
         },
         "size": {
            "x": 8.32806307372823,
            "y": 16.081776969957957
         },
         "object_id": 4
      },
      {
         "label_type": "box",
         "label_class": "R",
         "centre": {
            "x": 268.7454166596409,
            "y": 155.31018841524477
         },
         "size": {
            "x": 16.65612614745646,
            "y": 10.051110606223745
         },
         "object_id": 5
      },
      {
         "label_type": "box",
         "label_class": "R",
         "centre": {
            "x": 240.3151323734652,
            "y": 180.4379649308041
         },
         "size": {
            "x": 16.65612614745649,
            "y": 9.763936017474464
         },
         "object_id": 6
      },
      {
         "label_type": "box",
         "label_class": "R",
         "centre": {
            "x": 268.45824207089163,
            "y": 180.43796493080407
         },
         "size": {
            "x": 16.081776969957957,
            "y": 9.189586839975988
         },
         "object_id": 7
      },
      {
         "label_type": "box",
         "label_class": "R",
         "centre": {
            "x": 267.96513406682845,
            "y": 203.57472048414374
         },
         "size": {
            "x": 16.656126147456405,
            "y": 10.912634372471473
         },
         "object_id": 8
      },
      {
         "label_type": "box",
         "label_class": "R",
         "centre": {
            "x": 268.3958959499523,
            "y": 227.1230367615822
         },
         "size": {
            "x": 17.51764991370419,
            "y": 10.338285194972968
         },
         "object_id": 9
      },
      {
         "label_type": "box",
         "label_class": "R",
         "centre": {
            "x": 267.8215467724538,
            "y": 251.1021149221445
         },
         "size": {
            "x": 15.794602381208733,
            "y": 8.902412251226707
         },
         "object_id": 10
      },
      {
         "label_type": "box",
         "label_class": "R",
         "centre": {
            "x": 268.2523086555777,
            "y": 275.2247803770814
         },
         "size": {
            "x": 17.23047532495491,
            "y": 8.902412251226735
         },
         "object_id": 11
      },
      {
         "label_type": "box",
         "label_class": "R",
         "centre": {
            "x": 189.54130929723937,
            "y": 340.07491606855126
         },
         "size": {
            "x": 23.114677639282746,
            "y": 48.50293012833106
         },
         "object_id": 12
      },
      {
         "label_type": "box",
         "label_class": "C",
         "centre": {
            "x": 83.06222049988762,
            "y": 398.051074737572
         },
         "size": {
            "x": 15.536094806731029,
            "y": 9.094299399062095
         },
         "object_id": 13
      },
      {
         "label_type": "box",
         "label_class": "R",
         "centre": {
            "x": 51.04270803235657,
            "y": 398.6194684500133
         },
         "size": {
            "x": 14.399307381848281,
            "y": 9.47322854068966
         },
         "object_id": 14
      },
      {
         "label_type": "box",
         "label_class": "C",
         "centre": {
            "x": 51.04270803235657,
            "y": 416.6186026773237
         },
         "size": {
            "x": 16.672882231613798,
            "y": 9.094299399062038
         },
         "object_id": 15
      },
      {
         "label_type": "box",
         "label_class": "R",
         "centre": {
            "x": 83.44114964151521,
            "y": 416.0502089648823
         },
         "size": {
            "x": 17.809669656496553,
            "y": 11.74680339045517
         },
         "object_id": 16
      },
      {
         "label_type": "box",
         "label_class": "C",
         "centre": {
            "x": 155.81661569238418,
            "y": 393.3144604672271
         },
         "size": {
            "x": 10.98894510720001,
            "y": 17.809669656496567
         },
         "object_id": 17
      },
      {
         "label_type": "box",
         "label_class": "C",
         "centre": {
            "x": 36.961775751267055,
            "y": 486.5641041896048
         },
         "size": {
            "x": 7.999999999999716,
            "y": 13.999999999999488
         },
         "object_id": 18
      },
      {
         "label_type": "box",
         "label_class": "C",
         "centre": {
            "x": 87.58309070893833,
            "y": 532.8115237263137
         },
         "size": {
            "x": 18.281561829217935,
            "y": 11.752432604497244
         },
         "object_id": 19
      },
      {
         "label_type": "box",
         "label_class": "D",
         "centre": {
            "x": 88.67127891305844,
            "y": 578.0801530177106
         },
         "size": {
            "x": 23.94014049064255,
            "y": 49.18610682622921
         },
         "object_id": 20
      },
      {
         "label_type": "box",
         "label_class": "C",
         "centre": {
            "x": 130.67534359209492,
            "y": 567.1982709765094
         },
         "size": {
            "x": 31.33982027865933,
            "y": 23.940140490642534
         },
         "object_id": 21
      },
      {
         "label_type": "box",
         "label_class": "R",
         "centre": {
            "x": 219.2366913731507,
            "y": 625.5014833816663
         },
         "size": {
            "x": 10.231086823944793,
            "y": 17.430740514868944
         },
         "object_id": 22
      },
      {
         "label_type": "box",
         "label_class": "R",
         "centre": {
            "x": 237.04636102964724,
            "y": 625.6909479524801
         },
         "size": {
            "x": 11.746803390455142,
            "y": 20.083244506261963
         },
         "object_id": 23
      },
      {
         "label_type": "box",
         "label_class": "R",
         "centre": {
            "x": 255.23495982777132,
            "y": 626.4488062357352
         },
         "size": {
            "x": 11.746803390455142,
            "y": 19.32538622300683
         },
         "object_id": 24
      },
      {
         "label_type": "box",
         "label_class": "D",
         "centre": {
            "x": 316.63172770735474,
            "y": 580.6177103585678
         },
         "size": {
            "x": 30.999999999998863,
            "y": 17.499999999999318
         },
         "object_id": 25
      },
      {
         "label_type": "box",
         "label_class": "D",
         "centre": {
            "x": 365.6317277073529,
            "y": 581.6177103585678
         },
         "size": {
            "x": 29.999999999998863,
            "y": 17.499999999999318
         },
         "object_id": 26
      },
      {
         "label_type": "box",
         "label_class": "R",
         "centre": {
            "x": 218.38172770735844,
            "y": 566.8677103585684
         },
         "size": {
            "x": 17.499999999999346,
            "y": 9.999999999999545
         },
         "object_id": 27
      },
      {
         "label_type": "box",
         "label_class": "R",
         "centre": {
            "x": 248.1317277073573,
            "y": 510.8677103585705
         },
         "size": {
            "x": 8.999999999999659,
            "y": 16.99999999999943
         },
         "object_id": 28
      },
      {
         "label_type": "box",
         "label_class": "C",
         "centre": {
            "x": 264.6317277073567,
            "y": 510.61771035857055
         },
         "size": {
            "x": 8.999999999999659,
            "y": 17.499999999999375
         },
         "object_id": 29
      },
      {
         "label_type": "box",
         "label_class": "R",
         "centre": {
            "x": 203.88172770735898,
            "y": 502.3677103585708
         },
         "size": {
            "x": 13.499999999999488,
            "y": 20.99999999999926
         },
         "object_id": 30
      },
      {
         "label_type": "box",
         "label_class": "R",
         "centre": {
            "x": 282.04411589723577,
            "y": 510.06796062439685
         },
         "size": {
            "x": 10.895564107029884,
            "y": 17.31929502779576
         },
         "object_id": 31
      },
      {
         "label_type": "box",
         "label_class": "R",
         "centre": {
            "x": 318.33539536506595,
            "y": 510.64562218481103
         },
         "size": {
            "x": 10.22618630848956,
            "y": 16.823725862353797
         },
         "object_id": 32
      },
      {
         "label_type": "box",
         "label_class": "C",
         "centre": {
            "x": 335.15912122741975,
            "y": 509.4910527628848
         },
         "size": {
            "x": 8.90667839771669,
            "y": 16.493848884660622
         },
         "object_id": 33
      },
      {
         "label_type": "box",
         "label_class": "R",
         "centre": {
            "x": 351.9828470897735,
            "y": 509.4910527628848
         },
         "size": {
            "x": 9.566432353103096,
            "y": 16.493848884660622
         },
         "object_id": 34
      },
      {
         "label_type": "box",
         "label_class": "R",
         "centre": {
            "x": 264.40050951222594,
            "y": 466.60704566276735
         },
         "size": {
            "x": 17.81335679543338,
            "y": 10.556063286182734
         },
         "object_id": 35
      },
      {
         "label_type": "box",
         "label_class": "R",
         "centre": {
            "x": 268.58483794738254,
            "y": 322.93178733249397
         },
         "size": {
            "x": 16.368951558707124,
            "y": 8.615237662477455
         },
         "object_id": 36
      },
      {
         "label_type": "box",
         "label_class": "C",
         "centre": {
            "x": 417.37801557929197,
            "y": 485.06952072744673
         },
         "size": {
            "x": 16.97573598427374,
            "y": 8.705505632960865
         },
         "object_id": 37
      },
      {
         "label_type": "box",
         "label_class": "R",
         "centre": {
            "x": 417.16037793846795,
            "y": 500.0865179443042
         },
         "size": {
            "x": 16.540460702625694,
            "y": 10.881882041201095
         },
         "object_id": 38
      },
      {
         "label_type": "box",
         "label_class": "R",
         "centre": {
            "x": 416.7251026568199,
            "y": 517.279891569402
         },
         "size": {
            "x": 16.540460702625694,
            "y": 10.446606759552992
         },
         "object_id": 39
      },
      {
         "label_type": "box",
         "label_class": "C",
         "centre": {
            "x": 417.81329086094,
            "y": 534.2556275536757
         },
         "size": {
            "x": 17.846286547569832,
            "y": 8.705505632960922
         },
         "object_id": 40
      },
      {
         "label_type": "box",
         "label_class": "C",
         "centre": {
            "x": 416.9427402976439,
            "y": 549.7079000521812
         },
         "size": {
            "x": 16.97573598427374,
            "y": 8.270230351312762
         },
         "object_id": 41
      },
      {
         "label_type": "box",
         "label_class": "C",
         "centre": {
            "x": 416.28982737517185,
            "y": 567.3365489589271
         },
         "size": {
            "x": 20.893213519106155,
            "y": 12.18770788614529
         },
         "object_id": 42
      },
      {
         "label_type": "box",
         "label_class": "D",
         "centre": {
            "x": 425.86588357142887,
            "y": 589.5355883229773
         },
         "size": {
            "x": 32.21037084195524,
            "y": 17.411011265921843
         },
         "object_id": 43
      },
      {
         "label_type": "box",
         "label_class": "D",
         "centre": {
            "x": 425.64824593060484,
            "y": 612.1699029686756
         },
         "size": {
            "x": 32.645646123603285,
            "y": 15.669910139329545
         },
         "object_id": 44
      },
      {
         "label_type": "box",
         "label_class": "C",
         "centre": {
            "x": 428.2598976204931,
            "y": 631.1043777203656
         },
         "size": {
            "x": 16.97573598427374,
            "y": 9.140780914608854
         },
         "object_id": 45
      },
      {
         "label_type": "box",
         "label_class": "R",
         "centre": {
            "x": 485.46984054437314,
            "y": 655.0189826870436
         },
         "size": {
            "x": 9.236555375409864,
            "y": 15.504217951580813
         },
         "object_id": 46
      },
      {
         "label_type": "box",
         "label_class": "R",
         "centre": {
            "x": 508.89110596059106,
            "y": 649.7409510439522
         },
         "size": {
            "x": 16.49384888466051,
            "y": 10.88594026387591
         },
         "object_id": 47
      },
      {
         "label_type": "box",
         "label_class": "R",
         "centre": {
            "x": 509.2209829382843,
            "y": 667.2244308616924
         },
         "size": {
            "x": 15.834094929274102,
            "y": 8.246924442330283
         },
         "object_id": 48
      },
      {
         "label_type": "box",
         "label_class": "R",
         "centre": {
            "x": 509.05604444943765,
            "y": 683.8832182351995
         },
         "size": {
            "x": 16.163971906967333,
            "y": 10.556063286182734
         },
         "object_id": 49
      },
      {
         "label_type": "box",
         "label_class": "R",
         "centre": {
            "x": 479.696993434742,
            "y": 703.0160829414057
         },
         "size": {
            "x": 15.50421795158087,
            "y": 10.556063286182734
         },
         "object_id": 50
      },
      {
         "label_type": "box",
         "label_class": "R",
         "centre": {
            "x": 479.5320549458954,
            "y": 720.004747292606
         },
         "size": {
            "x": 16.49384888466051,
            "y": 8.906678397716632
         },
         "object_id": 51
      },
      {
         "label_type": "box",
         "label_class": "R",
         "centre": {
            "x": 479.696993434742,
            "y": 736.663534666113
         },
         "size": {
            "x": 16.163971906967276,
            "y": 9.89630933079627
         },
         "object_id": 52
      },
      {
         "label_type": "box",
         "label_class": "C",
         "centre": {
            "x": 508.5612289828979,
            "y": 700.3770671198599
         },
         "size": {
            "x": 15.174340973887695,
            "y": 9.236555375409921
         },
         "object_id": 53
      },
      {
         "label_type": "box",
         "label_class": "R",
         "centre": {
            "x": 560.8696319765404,
            "y": 577.6257963977622
         },
         "size": {
            "x": 8.249999999999659,
            "y": 15.499999999999318
         },
         "object_id": 54
      },
      {
         "label_type": "box",
         "label_class": "C",
         "centre": {
            "x": 530.2446319765418,
            "y": 525.5007963977645
         },
         "size": {
            "x": 7.499999999999659,
            "y": 14.249999999999318
         },
         "object_id": 55
      },
      {
         "label_type": "box",
         "label_class": "R",
         "centre": {
            "x": 624.8366280281848,
            "y": 482.0716150065855
         },
         "size": {
            "x": 19.58738767416196,
            "y": 10.881882041201095
         },
         "object_id": 56
      },
      {
         "label_type": "box",
         "label_class": "R",
         "centre": {
            "x": 659.4410129192042,
            "y": 482.72452792905756
         },
         "size": {
            "x": 16.540460702625637,
            "y": 11.317157322849084
         },
         "object_id": 57
      },
      {
         "label_type": "box",
         "label_class": "R",
         "centre": {
            "x": 696.2217742184639,
            "y": 470.10154476126434
         },
         "size": {
            "x": 9.140780914608968,
            "y": 14.79935957603351
         },
         "object_id": 58
      },
      {
         "label_type": "box",
         "label_class": "R",
         "centre": {
            "x": 651.4518433659882,
            "y": 122.9410915787416
         },
         "size": {
            "x": 18.716837110865868,
            "y": 9.140780914608897
         },
         "object_id": 59
      },
      {
         "label_type": "box",
         "label_class": "D",
         "centre": {
            "x": 682.7916636446473,
            "y": 123.8116421420377
         },
         "size": {
            "x": 16.975735984273683,
            "y": 8.270230351312819
         },
         "object_id": 60
      },
      {
         "label_type": "box",
         "label_class": "D",
         "centre": {
            "x": 683.2269389262954,
            "y": 140.78737812631138
         },
         "size": {
            "x": 16.975735984273683,
            "y": 9.14078091460891
         },
         "object_id": 61
      },
      {
         "label_type": "box",
         "label_class": "D",
         "centre": {
            "x": 683.4445765671194,
            "y": 159.2865775963532
         },
         "size": {
            "x": 17.41101126592173,
            "y": 8.705505632960865
         },
         "object_id": 62
      },
      {
         "label_type": "box",
         "label_class": "D",
         "centre": {
            "x": 683.0093012854713,
            "y": 177.78577706639504
         },
         "size": {
            "x": 18.28156182921782,
            "y": 8.270230351312819
         },
         "object_id": 63
      },
      {
         "label_type": "box",
         "label_class": "R",
         "centre": {
            "x": 652.1047562884603,
            "y": 141.2226534079594
         },
         "size": {
            "x": 16.540460702625637,
            "y": 10.011331477904974
         },
         "object_id": 64
      },
      {
         "label_type": "box",
         "label_class": "R",
         "centre": {
            "x": 652.1047562884603,
            "y": 158.4160270330571
         },
         "size": {
            "x": 18.28156182921782,
            "y": 9.576056196256928
         },
         "object_id": 65
      },
      {
         "label_type": "box",
         "label_class": "R",
         "centre": {
            "x": 652.9753068517564,
            "y": 177.13286414392297
         },
         "size": {
            "x": 16.540460702625637,
            "y": 10.44660675955302
         },
         "object_id": 66
      },
      {
         "label_type": "box",
         "label_class": "R",
         "centre": {
            "x": 636.6524837899549,
            "y": 202.16119283868545
         },
         "size": {
            "x": 17.846286547569775,
            "y": 10.011331477904974
         },
         "object_id": 67
      },
      {
         "label_type": "box",
         "label_class": "R",
         "centre": {
            "x": 636.2172085083068,
            "y": 221.53094287202336
         },
         "size": {
            "x": 16.975735984273683,
            "y": 8.705505632960865
         },
         "object_id": 68
      },
      {
         "label_type": "box",
         "label_class": "R",
         "centre": {
            "x": 664.5101018154296,
            "y": 240.03014234206518
         },
         "size": {
            "x": 9.140780914608854,
            "y": 16.10518542097759
         },
         "object_id": 69
      },
      {
         "label_type": "box",
         "label_class": "R",
         "centre": {
            "x": 691.0618939959602,
            "y": 243.2947069544255
         },
         "size": {
            "x": 9.140780914608968,
            "y": 15.669910139329545
         },
         "object_id": 70
      },
      {
         "label_type": "box",
         "label_class": "R",
         "centre": {
            "x": 634.4761073817147,
            "y": 249.1709232566741
         },
         "size": {
            "x": 16.10518542097759,
            "y": 7.399679788016726
         },
         "object_id": 71
      },
      {
         "label_type": "box",
         "label_class": "R",
         "centre": {
            "x": 634.4761073817147,
            "y": 268.75831093083605
         },
         "size": {
            "x": 15.234634857681499,
            "y": 9.14078091460891
         },
         "object_id": 72
      },
      {
         "label_type": "box",
         "label_class": "R",
         "centre": {
            "x": 634.4761073817147,
            "y": 287.91042332334996
         },
         "size": {
            "x": 16.10518542097759,
            "y": 9.14078091460891
         },
         "object_id": 73
      },
      {
         "label_type": "box",
         "label_class": "R",
         "centre": {
            "x": 634.6937450225387,
            "y": 307.4978109975118
         },
         "size": {
            "x": 14.799359576033453,
            "y": 9.14078091460891
         },
         "object_id": 74
      },
      {
         "label_type": "box",
         "label_class": "R",
         "centre": {
            "x": 623.6231238223132,
            "y": 348.3718675411533
         },
         "size": {
            "x": 9.189586839975846,
            "y": 16.081776969957787
         },
         "object_id": 75
      },
      {
         "label_type": "box",
         "label_class": "D",
         "centre": {
            "x": 37.158058266442936,
            "y": 448.88970514662344
         },
         "size": {
            "x": 15.915023948358435,
            "y": 30.314331330206528
         },
         "object_id": 76
      },
      {
         "label_type": "polygon",
         "label_class": "C",
         "vertices": [
            {
               "x": 110.43871637085005,
               "y": 325.23453269658546
            },
            {
               "x": 100.67478035337571,
               "y": 325.80888187408397
            },
            {
               "x": 99.81325658712795,
               "y": 393.2949102301565
            },
            {
               "x": 103.83370082961738,
               "y": 395.30513235140126
            },
            {
               "x": 111.87458931459624,
               "y": 395.017957762652
            },
            {
               "x": 113.88481143584096,
               "y": 401.04862412638613
            },
            {
               "x": 128.2435408733032,
               "y": 401.04862412638613
            },
            {
               "x": 130.82811217204642,
               "y": 394.73078317390275
            },
            {
               "x": 142.60227031076545,
               "y": 394.15643399640425
            },
            {
               "x": 143.75096866576243,
               "y": 326.9575802290809
            },
            {
               "x": 140.87922277827,
               "y": 324.9473581078362
            },
            {
               "x": 132.55115970454187,
               "y": 324.66018351908696
            },
            {
               "x": 131.11528676079567,
               "y": 320.06539009909903
            },
            {
               "x": 112.44893849209473,
               "y": 320.35256468784826
            }
         ],
         "object_id": 77
      },
      {
         "label_type": "polygon",
         "label_class": "L",
         "vertices": [
            {
               "x": 176.97100970095985,
               "y": 418.91584441591067
            },
            {
               "x": 173.2377400472197,
               "y": 414.0338764071735
            },
            {
               "x": 110.92085428863354,
               "y": 414.32105099592275
            },
            {
               "x": 107.76193381239185,
               "y": 418.05432064966294
            },
            {
               "x": 107.47475922364261,
               "y": 479.50968264200134
            },
            {
               "x": 110.0593305223858,
               "y": 484.10447606198926
            },
            {
               "x": 125.27958372609578,
               "y": 484.965999828237
            },
            {
               "x": 134.18199597732237,
               "y": 484.67882523948776
            },
            {
               "x": 136.19221809856708,
               "y": 486.4018727719832
            },
            {
               "x": 153.4226934235218,
               "y": 486.4018727719832
            },
            {
               "x": 153.4226934235218,
               "y": 484.10447606198926
            },
            {
               "x": 173.5249146359689,
               "y": 484.67882523948776
            },
            {
               "x": 176.68383511221063,
               "y": 480.94555558574757
            }
         ],
         "object_id": 78
      },
      {
         "label_type": "polygon",
         "label_class": "D",
         "vertices": [
            {
               "x": 143.70397854948283,
               "y": 497.346505091768
            },
            {
               "x": 135.17807286286225,
               "y": 497.72543423339556
            },
            {
               "x": 136.31486028774498,
               "y": 539.9760335248709
            },
            {
               "x": 142.1882619829725,
               "y": 541.3022855205674
            },
            {
               "x": 142.75665569541388,
               "y": 545.4705060784707
            },
            {
               "x": 163.21882934330324,
               "y": 545.281041507657
            },
            {
               "x": 163.59775848493084,
               "y": 539.7865689540571
            },
            {
               "x": 169.66062475097215,
               "y": 539.4076398124295
            },
            {
               "x": 171.74473502992382,
               "y": 535.8078129669675
            },
            {
               "x": 171.93419960073763,
               "y": 499.0516862290921
            },
            {
               "x": 163.02936477248946,
               "y": 497.1570405209542
            },
            {
               "x": 162.2715064892343,
               "y": 493.1782845338646
            },
            {
               "x": 161.32418363516535,
               "y": 490.5257805424715
            },
            {
               "x": 142.94612026622767,
               "y": 490.5257805424715
            }
         ],
         "object_id": 79
      },
      {
         "label_type": "polygon",
         "label_class": "Q",
         "vertices": [
            {
               "x": 57.2890940997855,
               "y": 432.9658486401282
            },
            {
               "x": 56.15230667490276,
               "y": 444.3337228889556
            },
            {
               "x": 53.49980268350969,
               "y": 444.52318745976936
            },
            {
               "x": 52.36301525862695,
               "y": 478.2478810646241
            },
            {
               "x": 56.34177124571655,
               "y": 480.71092048520336
            },
            {
               "x": 57.09962952897171,
               "y": 494.9207632962376
            },
            {
               "x": 63.54142493664059,
               "y": 494.54183415461006
            },
            {
               "x": 63.35196036582679,
               "y": 480.90038505601717
            },
            {
               "x": 68.65696834861292,
               "y": 481.0898496268309
            },
            {
               "x": 68.65696834861292,
               "y": 495.11022786705144
            },
            {
               "x": 74.34090547302664,
               "y": 494.73129872542387
            },
            {
               "x": 75.0987637562818,
               "y": 481.4687787684585
            },
            {
               "x": 80.21430716825414,
               "y": 481.27931419764474
            },
            {
               "x": 80.78270088069551,
               "y": 494.54183415461006
            },
            {
               "x": 86.27717343429543,
               "y": 494.73129872542387
            },
            {
               "x": 86.84556714673681,
               "y": 481.0898496268309
            },
            {
               "x": 92.52950427115051,
               "y": 480.71092048520336
            },
            {
               "x": 93.28736255440568,
               "y": 494.54183415461006
            },
            {
               "x": 98.78183510800561,
               "y": 494.73129872542387
            },
            {
               "x": 98.97129967881939,
               "y": 480.52145591438955
            },
            {
               "x": 101.62380367021247,
               "y": 476.7321644981138
            },
            {
               "x": 101.43433909939867,
               "y": 446.4178331679073
            },
            {
               "x": 98.21344139556423,
               "y": 443.5758646057004
            },
            {
               "x": 98.78183510800561,
               "y": 432.3974549276868
            },
            {
               "x": 93.09789798359189,
               "y": 432.207990356873
            },
            {
               "x": 92.52950427115051,
               "y": 443.95479374732804
            },
            {
               "x": 86.46663800510923,
               "y": 443.76532917651423
            },
            {
               "x": 86.84556714673681,
               "y": 432.207990356873
            },
            {
               "x": 80.9721654515093,
               "y": 432.207990356873
            },
            {
               "x": 80.40377173906793,
               "y": 443.5758646057004
            },
            {
               "x": 74.15144090221285,
               "y": 443.38640003488666
            },
            {
               "x": 74.71983461465422,
               "y": 432.3974549276868
            },
            {
               "x": 69.60429120268188,
               "y": 432.3974549276868
            },
            {
               "x": 68.27803920698534,
               "y": 443.76532917651423
            },
            {
               "x": 62.59410208257163,
               "y": 443.5758646057004
            },
            {
               "x": 62.59410208257163,
               "y": 432.5869194985006
            }
         ],
         "object_id": 80
      },
      {
         "label_type": "box",
         "label_class": "D",
         "centre": {
            "x": 161.90001745344534,
            "y": 643.5654928874953
         },
         "size": {
            "x": 16.540460702625495,
            "y": 34.38674725019507
         },
         "object_id": 81
      },
      {
         "label_type": "polygon",
         "label_class": "Q",
         "vertices": [
            {
               "x": 222.8365678608436,
               "y": 587.9087779640957
            },
            {
               "x": 210.77523513337533,
               "y": 588.1959525528449
            },
            {
               "x": 210.77523513337533,
               "y": 582.4524607778601
            },
            {
               "x": 207.9034892458829,
               "y": 583.3139845441078
            },
            {
               "x": 206.18044171338744,
               "y": 588.7703017303435
            },
            {
               "x": 203.88304500339348,
               "y": 589.0574763190926
            },
            {
               "x": 203.88304500339348,
               "y": 599.970110691564
            },
            {
               "x": 213.35980643211855,
               "y": 601.118809046561
            },
            {
               "x": 214.79567937586475,
               "y": 606.000777055298
            },
            {
               "x": 220.53917115084965,
               "y": 606.000777055298
            },
            {
               "x": 220.82634573959888,
               "y": 600.2572852803132
            },
            {
               "x": 231.73898011207015,
               "y": 600.2572852803132
            },
            {
               "x": 231.45180552332093,
               "y": 588.4831271415942
            },
            {
               "x": 228.29288504707924,
               "y": 587.6216033753465
            },
            {
               "x": 227.71853586958073,
               "y": 581.8781116003615
            },
            {
               "x": 223.98526621584057,
               "y": 582.1652861891108
            }
         ],
         "object_id": 82
      },
      {
         "label_type": "polygon",
         "label_class": "Q",
         "vertices": [
            {
               "x": 234.2455816962502,
               "y": 547.7630052844502
            },
            {
               "x": 224.0193953877608,
               "y": 547.1032513290637
            },
            {
               "x": 224.0193953877608,
               "y": 536.8770650205744
            },
            {
               "x": 225.99865725392004,
               "y": 537.2069419982676
            },
            {
               "x": 226.65841120930645,
               "y": 531.2691563997898
            },
            {
               "x": 230.28705796393172,
               "y": 530.6094024444035
            },
            {
               "x": 230.61693494162492,
               "y": 535.8874340874947
            },
            {
               "x": 243.8120140493532,
               "y": 536.2173110651879
            },
            {
               "x": 244.8016449824328,
               "y": 529.6197715113238
            },
            {
               "x": 248.4302917370581,
               "y": 529.6197715113238
            },
            {
               "x": 249.0900456924445,
               "y": 535.8874340874947
            },
            {
               "x": 251.72906151399016,
               "y": 535.8874340874947
            },
            {
               "x": 251.06930755860375,
               "y": 547.433128306757
            },
            {
               "x": 239.1937363616483,
               "y": 547.7630052844502
            },
            {
               "x": 239.1937363616483,
               "y": 554.3605448383144
            },
            {
               "x": 235.56508960702303,
               "y": 554.0306678606211
            }
         ],
         "object_id": 83
      },
      {
         "label_type": "polygon",
         "label_class": "Q",
         "vertices": [
            {
               "x": 261.38568708160244,
               "y": 536.5568306468751
            },
            {
               "x": 259.68050594427837,
               "y": 536.9357597885028
            },
            {
               "x": 259.68050594427837,
               "y": 547.9247048957026
            },
            {
               "x": 270.47998648066437,
               "y": 548.3036340373302
            },
            {
               "x": 271.04838019310574,
               "y": 553.0402483076749
            },
            {
               "x": 275.21660075100914,
               "y": 553.0402483076749
            },
            {
               "x": 275.97445903426427,
               "y": 548.3036340373302
            },
            {
               "x": 286.7739395706503,
               "y": 547.7352403248888
            },
            {
               "x": 287.1528687122779,
               "y": 537.1252243593166
            },
            {
               "x": 283.7425064376297,
               "y": 536.3673660760613
            },
            {
               "x": 284.12143557925725,
               "y": 531.4412872349028
            },
            {
               "x": 280.3321441629814,
               "y": 530.8728935224615
            },
            {
               "x": 279.0058921672849,
               "y": 536.1779015052476
            },
            {
               "x": 266.6906950643886,
               "y": 536.746295217689
            },
            {
               "x": 266.6906950643886,
               "y": 530.6834289516477
            },
            {
               "x": 262.711939077299,
               "y": 530.6834289516477
            }
         ],
         "object_id": 84
      },
      {
         "label_type": "polygon",
         "label_class": "Q",
         "vertices": [
            {
               "x": 314.24630233864985,
               "y": 535.79897236362
            },
            {
               "x": 301.5521760941259,
               "y": 536.1779015052476
            },
            {
               "x": 302.1205698065673,
               "y": 530.4939643808339
            },
            {
               "x": 297.5734201070363,
               "y": 530.6834289516477
            },
            {
               "x": 296.81556182378114,
               "y": 536.746295217689
            },
            {
               "x": 294.7314515448295,
               "y": 537.1252243593166
            },
            {
               "x": 294.5419869740157,
               "y": 548.1141694665164
            },
            {
               "x": 305.7203966520293,
               "y": 548.1141694665164
            },
            {
               "x": 306.28879036447063,
               "y": 555.1243585866266
            },
            {
               "x": 311.40433377644297,
               "y": 555.1243585866266
            },
            {
               "x": 311.40433377644297,
               "y": 547.545775754075
            },
            {
               "x": 322.3932788836428,
               "y": 547.9247048957026
            },
            {
               "x": 322.5827434544566,
               "y": 537.3146889301303
            },
            {
               "x": 319.1723811798084,
               "y": 536.3673660760613
            },
            {
               "x": 319.9302394630635,
               "y": 529.9255706683925
            },
            {
               "x": 315.7620189051602,
               "y": 530.1150352392063
            }
         ],
         "object_id": 85
      },
      {
         "label_type": "polygon",
         "label_class": "Q",
         "vertices": [
            {
               "x": 350.0551062224561,
               "y": 535.4200432219924
            },
            {
               "x": 337.7399091195598,
               "y": 535.4200432219924
            },
            {
               "x": 337.7399091195598,
               "y": 529.1677123851374
            },
            {
               "x": 333.003294849215,
               "y": 529.3571769559511
            },
            {
               "x": 332.2454365659599,
               "y": 536.3673660760613
            },
            {
               "x": 330.54025542863576,
               "y": 536.5568306468751
            },
            {
               "x": 330.72971999944957,
               "y": 547.1668466124474
            },
            {
               "x": 341.52920053583557,
               "y": 547.9247048957026
            },
            {
               "x": 341.7186651066494,
               "y": 554.9348940158128
            },
            {
               "x": 346.2658148061803,
               "y": 554.745429444999
            },
            {
               "x": 346.6447439478079,
               "y": 547.545775754075
            },
            {
               "x": 358.2020827674491,
               "y": 547.7352403248888
            },
            {
               "x": 358.2020827674491,
               "y": 536.3673660760613
            },
            {
               "x": 354.79172049280083,
               "y": 535.79897236362
            },
            {
               "x": 354.6022559219871,
               "y": 529.1677123851374
            },
            {
               "x": 350.6234999348975,
               "y": 529.1677123851374
            }
         ],
         "object_id": 86
      },
      {
         "label_type": "polygon",
         "label_class": "Q",
         "vertices": [
            {
               "x": 453.303743149116,
               "y": 558.794819926476
            },
            {
               "x": 437.19855772813855,
               "y": 558.794819926476
            },
            {
               "x": 438.06910829143465,
               "y": 474.7866905684046
            },
            {
               "x": 454.6095689940601,
               "y": 473.9161400051085
            },
            {
               "x": 455.4801195573562,
               "y": 466.0811849354438
            },
            {
               "x": 501.61929941204824,
               "y": 466.0811849354438
            },
            {
               "x": 503.79567582028847,
               "y": 473.0455894418124
            },
            {
               "x": 520.7714118045619,
               "y": 474.35141528675655
            },
            {
               "x": 519.9008612412658,
               "y": 557.92426936318
            },
            {
               "x": 502.0545746936963,
               "y": 559.665370489772
            },
            {
               "x": 501.61929941204824,
               "y": 564.8886738695485
            },
            {
               "x": 454.17429371241207,
               "y": 564.8886738695485
            }
         ],
         "object_id": 87
      },
      {
         "label_type": "polygon",
         "label_class": "Q",
         "vertices": [
            {
               "x": 475.938057794814,
               "y": 581.864409853822
            },
            {
               "x": 472.8911308232777,
               "y": 582.7349604171181
            },
            {
               "x": 472.8911308232777,
               "y": 623.6508368920337
            },
            {
               "x": 475.938057794814,
               "y": 625.8272133002739
            },
            {
               "x": 476.80860835811006,
               "y": 636.2738200598269
            },
            {
               "x": 518.1597601146738,
               "y": 635.8385447781789
            },
            {
               "x": 518.1597601146738,
               "y": 625.3919380186259
            },
            {
               "x": 520.7714118045619,
               "y": 623.2155616103857
            },
            {
               "x": 521.20668708621,
               "y": 581.429134572174
            },
            {
               "x": 518.1597601146738,
               "y": 580.5585840088779
            },
            {
               "x": 517.2892095513777,
               "y": 570.111977249325
            },
            {
               "x": 475.938057794814,
               "y": 570.111977249325
            }
         ],
         "object_id": 88
      },
      {
         "label_type": "polygon",
         "label_class": "Misc",
         "vertices": [
            {
               "x": 560.4211713213093,
               "y": 625.4119548759983
            },
            {
               "x": 560.4211713213093,
               "y": 657.1870504363051
            },
            {
               "x": 540.8337836471476,
               "y": 658.0576009996012
            },
            {
               "x": 540.8337836471476,
               "y": 666.763106632562
            },
            {
               "x": 560.8564466029572,
               "y": 667.633657195858
            },
            {
               "x": 563.0328230111975,
               "y": 670.2453088857462
            },
            {
               "x": 618.3127837804983,
               "y": 669.8100336040982
            },
            {
               "x": 620.4891601887385,
               "y": 666.763106632562
            },
            {
               "x": 637.90017145466,
               "y": 666.763106632562
            },
            {
               "x": 637.90017145466,
               "y": 659.3634268445453
            },
            {
               "x": 620.9244354703866,
               "y": 658.9281515628973
            },
            {
               "x": 620.4891601887385,
               "y": 625.8472301576463
            },
            {
               "x": 638.7707220179561,
               "y": 625.4119548759983
            },
            {
               "x": 637.464896173012,
               "y": 616.7064492430376
            },
            {
               "x": 619.6186096254424,
               "y": 616.2711739613895
            },
            {
               "x": 619.6186096254424,
               "y": 611.4831458632611
            },
            {
               "x": 561.2917218846053,
               "y": 611.9184211449091
            },
            {
               "x": 560.4211713213093,
               "y": 615.4006233980934
            },
            {
               "x": 539.5279578022034,
               "y": 615.8358986797415
            },
            {
               "x": 540.3985083654995,
               "y": 624.9766795943502
            }
         ],
         "object_id": 89
      },
      {
         "label_type": "polygon",
         "label_class": "Misc",
         "vertices": [
            {
               "x": 617.9156047103711,
               "y": 682.8917005045591
            },
            {
               "x": 559.3319886055255,
               "y": 684.040398859556
            },
            {
               "x": 559.906337783024,
               "y": 688.0608431020455
            },
            {
               "x": 539.2297673930785,
               "y": 688.9223668682932
            },
            {
               "x": 539.2297673930785,
               "y": 696.1017315870242
            },
            {
               "x": 559.0448140167763,
               "y": 696.963255353272
            },
            {
               "x": 560.1935123717732,
               "y": 730.8498568256827
            },
            {
               "x": 540.952814925574,
               "y": 731.1370314144319
            },
            {
               "x": 541.8143386918217,
               "y": 738.6035707219122
            },
            {
               "x": 559.0448140167763,
               "y": 738.8907453106615
            },
            {
               "x": 559.3319886055255,
               "y": 742.9111895531508
            },
            {
               "x": 617.9156047103711,
               "y": 742.9111895531508
            },
            {
               "x": 620.213001420365,
               "y": 738.8907453106615
            },
            {
               "x": 637.1563021565703,
               "y": 738.6035707219122
            },
            {
               "x": 637.7306513340689,
               "y": 731.4242060031811
            },
            {
               "x": 619.6386522428666,
               "y": 730.5626822369334
            },
            {
               "x": 619.3514776541173,
               "y": 696.1017315870242
            },
            {
               "x": 637.1563021565703,
               "y": 696.1017315870242
            },
            {
               "x": 637.1563021565703,
               "y": 688.3480176907947
            },
            {
               "x": 619.064303065368,
               "y": 687.7736685132962
            }
         ],
         "object_id": 90
      },
      {
         "label_type": "polygon",
         "label_class": "Misc",
         "vertices": [
            {
               "x": 676.4884012794552,
               "y": 612.4735895574568
            },
            {
               "x": 674.1792624356027,
               "y": 617.0918672451617
            },
            {
               "x": 653.7268898186239,
               "y": 617.751621200548
            },
            {
               "x": 653.7268898186239,
               "y": 624.6790377321054
            },
            {
               "x": 673.8493854579095,
               "y": 624.6790377321054
            },
            {
               "x": 673.8493854579095,
               "y": 659.9758743452783
            },
            {
               "x": 654.3866437740104,
               "y": 659.6459973675851
            },
            {
               "x": 653.7268898186239,
               "y": 668.2227987876084
            },
            {
               "x": 673.8493854579095,
               "y": 667.2331678545288
            },
            {
               "x": 673.5195084802162,
               "y": 671.8514455422337
            },
            {
               "x": 732.5674874873,
               "y": 671.1916915868472
            },
            {
               "x": 733.5571184203797,
               "y": 667.2331678545288
            },
            {
               "x": 750.7107212604262,
               "y": 667.2331678545288
            },
            {
               "x": 751.0405982381195,
               "y": 659.9758743452783
            },
            {
               "x": 734.5467493534592,
               "y": 659.6459973675851
            },
            {
               "x": 734.216872375766,
               "y": 625.0089147097985
            },
            {
               "x": 750.380844282733,
               "y": 625.3387916874917
            },
            {
               "x": 750.7107212604262,
               "y": 616.7619902674684
            },
            {
               "x": 733.5571184203797,
               "y": 617.0918672451617
            },
            {
               "x": 733.2272414426864,
               "y": 611.8138356020703
            }
         ],
         "object_id": 91
      },
      {
         "label_type": "polygon",
         "label_class": "Misc",
         "vertices": [
            {
               "x": 675.1646031606385,
               "y": 683.6679982678304
            },
            {
               "x": 674.0764149565185,
               "y": 687.5854758026628
            },
            {
               "x": 653.1832014374127,
               "y": 688.0207510843107
            },
            {
               "x": 653.6184767190607,
               "y": 695.6380685131514
            },
            {
               "x": 673.8587773156945,
               "y": 696.5086190764475
            },
            {
               "x": 674.0764149565185,
               "y": 730.8953663266425
            },
            {
               "x": 653.6184767190607,
               "y": 731.1130039674665
            },
            {
               "x": 654.0537520007088,
               "y": 738.0774084738351
            },
            {
               "x": 674.2940525973426,
               "y": 738.7303213963072
            },
            {
               "x": 675.1646031606385,
               "y": 742.6477989311395
            },
            {
               "x": 732.6209403381795,
               "y": 742.2125236494915
            },
            {
               "x": 733.7091285422996,
               "y": 738.5126837554832
            },
            {
               "x": 750.467226885749,
               "y": 738.5126837554832
            },
            {
               "x": 750.684864526573,
               "y": 731.3306416082905
            },
            {
               "x": 733.2738532606515,
               "y": 730.6777286858185
            },
            {
               "x": 733.2738532606515,
               "y": 696.0733437947995
            },
            {
               "x": 751.5554150898691,
               "y": 696.0733437947995
            },
            {
               "x": 751.3377774490451,
               "y": 688.0207510843107
            },
            {
               "x": 733.2738532606515,
               "y": 687.3678381618388
            },
            {
               "x": 732.6209403381795,
               "y": 683.6679982678304
            }
         ],
         "object_id": 92
      },
      {
         "label_type": "polygon",
         "label_class": "Misc",
         "vertices": [
            {
               "x": 637.0389645891104,
               "y": 518.8352686176124
            },
            {
               "x": 633.992037617574,
               "y": 521.4469203075007
            },
            {
               "x": 633.556762335926,
               "y": 576.5092434359774
            },
            {
               "x": 637.0389645891104,
               "y": 578.0327069217454
            },
            {
               "x": 637.0389645891104,
               "y": 596.7495440326111
            },
            {
               "x": 645.526832581247,
               "y": 597.1848193142591
            },
            {
               "x": 646.3973831445431,
               "y": 577.5974316400974
            },
            {
               "x": 680.131217472266,
               "y": 577.8150692809214
            },
            {
               "x": 679.478304549794,
               "y": 596.5319063917871
            },
            {
               "x": 687.9661725419306,
               "y": 596.9671816734351
            },
            {
               "x": 689.2719983868748,
               "y": 578.2503445625695
            },
            {
               "x": 692.7542006400591,
               "y": 578.2503445625695
            },
            {
               "x": 694.7129394074752,
               "y": 574.9857799502092
            },
            {
               "x": 694.7129394074752,
               "y": 521.2292826666767
            },
            {
               "x": 692.1012877175871,
               "y": 518.6176309767884
            },
            {
               "x": 688.8367231052267,
               "y": 518.6176309767884
            },
            {
               "x": 688.1838101827547,
               "y": 500.9889820700429
            },
            {
               "x": 680.7841303947381,
               "y": 501.2066197108669
            },
            {
               "x": 680.5664927539141,
               "y": 518.1823556951404
            },
            {
               "x": 646.1797455037191,
               "y": 518.1823556951404
            },
            {
               "x": 645.091557299599,
               "y": 499.4655185842748
            },
            {
               "x": 636.6036893074623,
               "y": 500.11843150674684
            }
         ],
         "object_id": 93
      },
      {
         "label_type": "polygon",
         "label_class": "Q",
         "vertices": [
            {
               "x": 619.912039396584,
               "y": 463.83452972498515
            },
            {
               "x": 618.2626545081179,
               "y": 471.0918232342357
            },
            {
               "x": 614.6340077534927,
               "y": 469.44243834576963
            },
            {
               "x": 614.9638847311859,
               "y": 465.15403763575796
            },
            {
               "x": 611.9949919319471,
               "y": 463.50465274729197
            },
            {
               "x": 611.6651149542538,
               "y": 453.6083434164958
            },
            {
               "x": 623.8705631289024,
               "y": 452.288835505723
            },
            {
               "x": 624.2004401065956,
               "y": 445.3614189741657
            },
            {
               "x": 628.8187177943005,
               "y": 446.0211729295521
            },
            {
               "x": 629.1485947719937,
               "y": 452.288835505723
            },
            {
               "x": 639.1853165096692,
               "y": 453.5525471676377
            },
            {
               "x": 639.7537102221106,
               "y": 463.9730985623961
            },
            {
               "x": 637.2906708015313,
               "y": 466.0572088413478
            },
            {
               "x": 636.5328125182762,
               "y": 469.8465002576236
            },
            {
               "x": 632.1751273895591,
               "y": 469.8465002576236
            },
            {
               "x": 632.1751273895591,
               "y": 465.10988598727886
            }
         ],
         "object_id": 94
      },
      {
         "label_type": "polygon",
         "label_class": "Q",
         "vertices": [
            {
               "x": 656.426592453724,
               "y": 453.17361802601016
            },
            {
               "x": 646.3849702005932,
               "y": 453.74201173845154
            },
            {
               "x": 646.7638993422207,
               "y": 464.5414922748375
            },
            {
               "x": 649.0374741919862,
               "y": 465.2993505580926
            },
            {
               "x": 649.0374741919862,
               "y": 469.8465002576236
            },
            {
               "x": 653.2056947498896,
               "y": 469.8465002576236
            },
            {
               "x": 653.3951593207033,
               "y": 464.92042141646505
            },
            {
               "x": 666.8471438484823,
               "y": 464.7309568456513
            },
            {
               "x": 666.6576792776685,
               "y": 469.2781065451822
            },
            {
               "x": 669.878576981503,
               "y": 469.467571115996
            },
            {
               "x": 670.6364352647581,
               "y": 464.5414922748375
            },
            {
               "x": 672.531080972896,
               "y": 464.5414922748375
            },
            {
               "x": 673.8573329685926,
               "y": 461.3205945710031
            },
            {
               "x": 673.6678683977788,
               "y": 452.98415345519635
            },
            {
               "x": 661.9210650073238,
               "y": 452.7946888843826
            },
            {
               "x": 661.1632067240687,
               "y": 448.0580746140379
            },
            {
               "x": 657.1844507369791,
               "y": 448.24753918485163
            }
         ],
         "object_id": 95
      },
      {
         "label_type": "polygon",
         "label_class": "C",
         "vertices": [
            {
               "x": 39.17663601737308,
               "y": 514.1019418909514
            },
            {
               "x": 25.96660493490797,
               "y": 514.3891164797006
            },
            {
               "x": 23.95638281366328,
               "y": 582.4494940132709
            },
            {
               "x": 27.115303289904936,
               "y": 584.1725415457663
            },
            {
               "x": 38.602286839874594,
               "y": 584.1725415457663
            },
            {
               "x": 38.88946142862384,
               "y": 588.7673349657541
            },
            {
               "x": 53.53536545483516,
               "y": 589.6288587320018
            },
            {
               "x": 54.68406380983212,
               "y": 583.0238431907693
            },
            {
               "x": 66.17104735980178,
               "y": 583.5981923682679
            },
            {
               "x": 67.31974571479874,
               "y": 581.8751448357724
            },
            {
               "x": 68.46844406979571,
               "y": 516.1121640121961
            },
            {
               "x": 67.0325711260495,
               "y": 514.6762910684498
            },
            {
               "x": 55.2584129873306,
               "y": 514.1019418909514
            },
            {
               "x": 54.39688922108288,
               "y": 507.4969263497188
            },
            {
               "x": 39.46381060612232,
               "y": 507.4969263497188
            }
         ],
         "object_id": 96
      },
      {
         "label_type": "polygon",
         "label_class": "Q",
         "vertices": [
            {
               "x": 678.4074707907596,
               "y": 216.58410909262813
            },
            {
               "x": 666.1574707907604,
               "y": 216.58410909262813
            },
            {
               "x": 665.6574707907604,
               "y": 222.08410909262778
            },
            {
               "x": 662.4074707907606,
               "y": 222.33410909262776
            },
            {
               "x": 661.4074707907607,
               "y": 216.8341090926281
            },
            {
               "x": 658.9074707907608,
               "y": 216.8341090926281
            },
            {
               "x": 658.6574707907608,
               "y": 206.08410909262878
            },
            {
               "x": 670.1574707907602,
               "y": 206.33410909262875
            },
            {
               "x": 669.9074707907602,
               "y": 198.58410909262923
            },
            {
               "x": 674.4074707907599,
               "y": 198.58410909262923
            },
            {
               "x": 674.9074707907598,
               "y": 204.58410909262886
            },
            {
               "x": 686.9074707907591,
               "y": 205.5841090926288
            },
            {
               "x": 686.9074707907591,
               "y": 216.8341090926281
            },
            {
               "x": 684.6574707907592,
               "y": 216.8341090926281
            },
            {
               "x": 683.9074707907592,
               "y": 221.33410909262784
            },
            {
               "x": 679.6574707907596,
               "y": 221.33410909262784
            }
         ],
         "object_id": 97
      },
      {
         "label_type": "polygon",
         "label_class": "Q",
         "vertices": [
            {
               "x": 705.6574707907579,
               "y": 203.83410909262892
            },
            {
               "x": 694.6574707907586,
               "y": 204.3341090926289
            },
            {
               "x": 693.9074707907587,
               "y": 207.3341090926287
            },
            {
               "x": 694.4074707907587,
               "y": 216.8341090926281
            },
            {
               "x": 697.1574707907585,
               "y": 216.8341090926281
            },
            {
               "x": 697.1574707907585,
               "y": 222.08410909262778
            },
            {
               "x": 701.1574707907582,
               "y": 221.83410909262778
            },
            {
               "x": 701.9074707907582,
               "y": 216.8341090926281
            },
            {
               "x": 714.9074707907573,
               "y": 216.8341090926281
            },
            {
               "x": 715.1574707907573,
               "y": 222.58410909262776
            },
            {
               "x": 719.1574707907571,
               "y": 222.58410909262776
            },
            {
               "x": 719.4074707907571,
               "y": 215.83410909262818
            },
            {
               "x": 721.657470790757,
               "y": 214.58410909262824
            },
            {
               "x": 722.1574707907569,
               "y": 205.83410909262878
            },
            {
               "x": 720.407470790757,
               "y": 204.3341090926289
            },
            {
               "x": 710.4074707907577,
               "y": 204.3341090926289
            },
            {
               "x": 710.1574707907577,
               "y": 199.0841090926292
            },
            {
               "x": 705.9074707907579,
               "y": 198.83410909262923
            }
         ],
         "object_id": 98
      },
      {
         "label_type": "box",
         "label_class": "Q",
         "centre": {
            "x": 299.50426695642074,
            "y": 472.86229127489116
         },
         "size": {
            "x": 18.80298772851245,
            "y": 20.78224959467167
         },
         "object_id": 99
      },
      {
         "label_type": "box",
         "label_class": "Misc",
         "centre": {
            "x": 542.582320005964,
            "y": 573.358632307159
         },
         "size": {
            "x": 18.37917367995135,
            "y": 33.59942688366084
         },
         "object_id": 101
      }
   ]
}